MANIFEST.in
README.md
changelog.md
setup.cfg
setup.py
ConfigSpace/__init__.py
ConfigSpace/__version__.py
ConfigSpace/c_util.pyx
ConfigSpace/conditions.pxd
ConfigSpace/conditions.pyx
ConfigSpace/configuration_space.py
ConfigSpace/convert.py
ConfigSpace/exceptions.py
ConfigSpace/forbidden.pxd
ConfigSpace/forbidden.pyx
ConfigSpace/hyperparameters.pxd
ConfigSpace/hyperparameters.pyx
ConfigSpace/util.py
ConfigSpace/nx/__init__.py
ConfigSpace/nx/exception.py
ConfigSpace/nx/release.py
ConfigSpace/nx/algorithms/__init__.py
ConfigSpace/nx/algorithms/cycles.py
ConfigSpace/nx/algorithms/dag.py
ConfigSpace/nx/algorithms/components/__init__.py
ConfigSpace/nx/algorithms/components/strongly_connected.py
ConfigSpace/nx/classes/__init__.py
ConfigSpace/nx/classes/digraph.py
ConfigSpace/nx/classes/graph.py
ConfigSpace/read_and_write/__init__.py
ConfigSpace/read_and_write/irace.py
ConfigSpace/read_and_write/json.py
ConfigSpace/read_and_write/pbs.py
ConfigSpace/read_and_write/pcs.py
ConfigSpace/read_and_write/pcs_new.py
ConfigSpace/read_and_write/pyll.py
ConfigSpace/read_and_write/spearmint_april2013_mod_spearmint_pb2.py
ConfigSpace_nni.egg-info/PKG-INFO
ConfigSpace_nni.egg-info/SOURCES.txt
ConfigSpace_nni.egg-info/dependency_links.txt
ConfigSpace_nni.egg-info/requires.txt
ConfigSpace_nni.egg-info/top_level.txt
test/__init__.py
test/test_conditions.py
test/test_configuration_space.py
test/test_forbidden.py
test/test_hyperparameters.py
test/test_util.py
test/read_and_write/__init__.py
test/read_and_write/test_irace_writer.py
test/read_and_write/test_json.py
test/read_and_write/test_pb_converter.py
test/read_and_write/test_pcs_converter.py
test/read_and_write/test_pyll_util.py
test/test_converters_and_test_searchspaces/__init__.py
test/test_converters_and_test_searchspaces/test_sample_configuration_spaces.py
test/test_searchspaces/__init__.py