Metadata-Version: 1.2
Name: ConfigSpace-nni
Version: 0.4.7
Summary: Creation and manipulation of parameter configuration spaces for automated algorithm configuration and hyperparameter tuning.
Home-page: https://github.com/QuanluZhang/ConfigSpace
Author: Matthias Feurer, Katharina Eggensperger, Syed Mohsin Ali, Christina Hernandez Wunsch, Julien-Charles Levesque, Jost Tobias Springenberg, Marius Lindauer, Jorn Tuyls, Quanlu Zhang
Author-email: nni@microsoft.com
License: BSD 3-clause
Keywords: algorithm configuration hyperparameter optimization empirical evaluation black box
Platform: Linux
Classifier: Programming Language :: Python :: 3.4
Classifier: Programming Language :: Python :: 3.5
Classifier: Programming Language :: Python :: 3.6
Classifier: Programming Language :: Python :: 3.7
Classifier: Development Status :: 4 - Beta
Classifier: Natural Language :: English
Classifier: Intended Audience :: Developers
Classifier: Intended Audience :: Education
Classifier: Intended Audience :: Science/Research
Classifier: License :: OSI Approved :: BSD License
Classifier: Operating System :: POSIX :: Linux
Classifier: Topic :: Scientific/Engineering :: Artificial Intelligence
Classifier: Topic :: Scientific/Engineering
Classifier: Topic :: Software Development
Requires-Python: >=3.4.*
